openai_costs_logger/__init__.py
openai_costs_logger/openai_costs_logger.py
openaiCostsLogger-0.1.1.dist-info/LICENSE.md
openaiCostsLogger-0.1.1.dist-info/METADATA
openaiCostsLogger-0.1.1.dist-info/WHEEL
openaiCostsLogger-0.1.1.dist-info/top_level.txt
openaiCostsLogger-0.1.1.dist-info/RECORD
