Metadata-Version: 2.1
Name: openaiCostsLogger
Version: 0.1.1
Summary: A utility for logging OpenAI API usage and costs.
Author-email: Tal Darom <tal.darom@gmail.com>
License: MIT License
Project-URL: Bug Tracker, https://github.com/talda/openaiCostsLogger/issues
Classifier: Development Status :: 3 - Alpha
Classifier: Intended Audience :: Developers
Classifier: License :: OSI Approved :: MIT License
Classifier: Programming Language :: Python :: 3
Classifier: Programming Language :: Python :: 3.7
Classifier: Programming Language :: Python :: 3.8
Classifier: Programming Language :: Python :: 3.9
License-File: LICENSE.md
